lolalytics_api/__init__.py
lolalytics_api/errors.py
lolalytics_api/main.py
lolalytics_api-0.0.6.dist-info/licenses/LICENSE
lolalytics_api-0.0.6.dist-info/METADATA
lolalytics_api-0.0.6.dist-info/WHEEL
lolalytics_api-0.0.6.dist-info/top_level.txt
lolalytics_api-0.0.6.dist-info/RECORD
