Metadata-Version: 2.4
Name: lolalytics-api
Version: 0.0.6
Summary: Unofficial Lolalytics scraper
Author: xPerSki
License: MIT
Project-URL: Homepage, https://github.com/xPerSki/lolalytics-api
Project-URL: Repository, https://github.com/xPerSki/lolalytics-api
Project-URL: Issues, https://github.com/xPerSki/lolalytics-api/issues
Classifier: Programming Language :: Python :: 3
Classifier: License :: OSI Approved :: MIT License
Classifier: Operating System :: OS Independent
Classifier: Topic :: Games/Entertainment
Classifier: Topic :: Internet :: WWW/HTTP :: Dynamic Content
Requires-Python: >=3.6
License-File: LICENSE
Requires-Dist: requests
Requires-Dist: lxml
Provides-Extra: test
Requires-Dist: pytest; extra == "test"
Dynamic: license-file
